setup.py
elastopy/__init__.py
elastopy/boundary.py
elastopy/constructor.py
elastopy/element.py
elastopy/material.py
elastopy/model.py
elastopy/newmark.py
elastopy/stress.py
elastopy.egg-info/PKG-INFO
elastopy.egg-info/SOURCES.txt
elastopy.egg-info/dependency_links.txt
elastopy.egg-info/not-zip-safe
elastopy.egg-info/requires.txt
elastopy.egg-info/top_level.txt