Metadata-Version: 1.1
Name: elastopy
Version: 0.3
Summary: Stead state linear elasticity problem
Home-page: https://github.com/nasseralkmim/elastopy
Author: Nasser Alkmim
Author-email: nasser.alkmim@gmail.com
License: GLP3
Download-URL: https://github.com/nasseralkmim/elastopy/releases/tag/0.3.1
Platform: UNKNOWN
